setup.py
risk_hedger/__init__.py
risk_hedger/risk_hedger.py
risk_hedger.egg-info/PKG-INFO
risk_hedger.egg-info/SOURCES.txt
risk_hedger.egg-info/dependency_links.txt
risk_hedger.egg-info/not-zip-safe
risk_hedger.egg-info/requires.txt
risk_hedger.egg-info/top_level.txt