Metadata-Version: 1.0
Name: risk-hedger
Version: 0.1
Summary: Risk Hedger powered by SliceMatrix-IO
Home-page: http://www.slicematrix.com/
Author: Hekaton LLC
Author-email: tynan@slicematrix.com
License: MIT
Platform: UNKNOWN
